{
  "creator": "Yosys 0.9 (git sha1 1979e0b)",
  "modules": {
    "sr_latch_nand": {
      "attributes": {
        "cells_not_processed": 1,
        "src": "/home/svs_06/Google-Girl-Hackathon/Data/RTL_Sources/rand57.v:1"
      },
      "ports": {
        "s": {
          "direction": "input",
          "bits": [ 2 ]
        },
        "r": {
          "direction": "input",
          "bits": [ 3 ]
        },
        "q": {
          "direction": "output",
          "bits": [ 4 ]
        },
        "q_bar": {
          "direction": "output",
          "bits": [ 5 ]
        }
      },
      "cells": {
        "$and$/home/svs_06/Google-Girl-Hackathon/Data/RTL_Sources/rand57.v:8$1": {
          "hide_name": 1,
          "type": "$and",
          "parameters": {
            "A_SIGNED": 0,
            "A_WIDTH": 1,
            "B_SIGNED": 0,
            "B_WIDTH": 1,
            "Y_WIDTH": 1
          },
          "attributes": {
            "src": "/home/svs_06/Google-Girl-Hackathon/Data/RTL_Sources/rand57.v:8"
          },
          "port_directions": {
            "A": "input",
            "B": "input",
            "Y": "output"
          },
          "connections": {
            "A": [ 2 ],
            "B": [ 5 ],
            "Y": [ 6 ]
          }
        },
        "$and$/home/svs_06/Google-Girl-Hackathon/Data/RTL_Sources/rand57.v:9$3": {
          "hide_name": 1,
          "type": "$and",
          "parameters": {
            "A_SIGNED": 0,
            "A_WIDTH": 1,
            "B_SIGNED": 0,
            "B_WIDTH": 1,
            "Y_WIDTH": 1
          },
          "attributes": {
            "src": "/home/svs_06/Google-Girl-Hackathon/Data/RTL_Sources/rand57.v:9"
          },
          "port_directions": {
            "A": "input",
            "B": "input",
            "Y": "output"
          },
          "connections": {
            "A": [ 3 ],
            "B": [ 4 ],
            "Y": [ 7 ]
          }
        },
        "$not$/home/svs_06/Google-Girl-Hackathon/Data/RTL_Sources/rand57.v:8$2": {
          "hide_name": 1,
          "type": "$not",
          "parameters": {
            "A_SIGNED": 0,
            "A_WIDTH": 1,
            "Y_WIDTH": 1
          },
          "attributes": {
            "src": "/home/svs_06/Google-Girl-Hackathon/Data/RTL_Sources/rand57.v:8"
          },
          "port_directions": {
            "A": "input",
            "Y": "output"
          },
          "connections": {
            "A": [ 6 ],
            "Y": [ 4 ]
          }
        },
        "$not$/home/svs_06/Google-Girl-Hackathon/Data/RTL_Sources/rand57.v:9$4": {
          "hide_name": 1,
          "type": "$not",
          "parameters": {
            "A_SIGNED": 0,
            "A_WIDTH": 1,
            "Y_WIDTH": 1
          },
          "attributes": {
            "src": "/home/svs_06/Google-Girl-Hackathon/Data/RTL_Sources/rand57.v:9"
          },
          "port_directions": {
            "A": "input",
            "Y": "output"
          },
          "connections": {
            "A": [ 7 ],
            "Y": [ 5 ]
          }
        }
      },
      "netnames": {
        "$and$/home/svs_06/Google-Girl-Hackathon/Data/RTL_Sources/rand57.v:8$1_Y": {
          "hide_name": 1,
          "bits": [ 6 ],
          "attributes": {
            "src": "/home/svs_06/Google-Girl-Hackathon/Data/RTL_Sources/rand57.v:8"
          }
        },
        "$and$/home/svs_06/Google-Girl-Hackathon/Data/RTL_Sources/rand57.v:9$3_Y": {
          "hide_name": 1,
          "bits": [ 7 ],
          "attributes": {
            "src": "/home/svs_06/Google-Girl-Hackathon/Data/RTL_Sources/rand57.v:9"
          }
        },
        "q": {
          "hide_name": 0,
          "bits": [ 4 ],
          "attributes": {
            "src": "/home/svs_06/Google-Girl-Hackathon/Data/RTL_Sources/rand57.v:4"
          }
        },
        "q_bar": {
          "hide_name": 0,
          "bits": [ 5 ],
          "attributes": {
            "src": "/home/svs_06/Google-Girl-Hackathon/Data/RTL_Sources/rand57.v:5"
          }
        },
        "r": {
          "hide_name": 0,
          "bits": [ 3 ],
          "attributes": {
            "src": "/home/svs_06/Google-Girl-Hackathon/Data/RTL_Sources/rand57.v:3"
          }
        },
        "s": {
          "hide_name": 0,
          "bits": [ 2 ],
          "attributes": {
            "src": "/home/svs_06/Google-Girl-Hackathon/Data/RTL_Sources/rand57.v:2"
          }
        }
      }
    }
  }
}
