{
  "$add$/home/svs_06/Google-Girl-Hackathon/Data/RTL_Sources/spi_master.v:131$21": {
    "cell_type": "$add",
    "signal_width": 32,
    "fan_in_count": 3,
    "has_multiply": 0,
    "has_divide": 0,
    "has_add": 1
  },
  "$add$/home/svs_06/Google-Girl-Hackathon/Data/RTL_Sources/spi_master.v:38$5": {
    "cell_type": "$add",
    "signal_width": 32,
    "fan_in_count": 3,
    "has_multiply": 0,
    "has_divide": 0,
    "has_add": 1
  },
  "$auto$opt_reduce.cc:126:opt_mux$106": {
    "cell_type": "$reduce_or",
    "signal_width": 2,
    "fan_in_count": 2,
    "has_multiply": 0,
    "has_divide": 0,
    "has_add": 0
  },
  "$auto$opt_reduce.cc:126:opt_mux$110": {
    "cell_type": "$reduce_or",
    "signal_width": 2,
    "fan_in_count": 2,
    "has_multiply": 0,
    "has_divide": 0,
    "has_add": 0
  },
  "$eq$/home/svs_06/Google-Girl-Hackathon/Data/RTL_Sources/spi_master.v:126$19": {
    "cell_type": "$eq",
    "signal_width": 8,
    "fan_in_count": 3,
    "has_multiply": 0,
    "has_divide": 0,
    "has_add": 0
  },
  "$eq$/home/svs_06/Google-Girl-Hackathon/Data/RTL_Sources/spi_master.v:76$9": {
    "cell_type": "$eq",
    "signal_width": 4,
    "fan_in_count": 3,
    "has_multiply": 0,
    "has_divide": 0,
    "has_add": 0
  },
  "$logic_and$/home/svs_06/Google-Girl-Hackathon/Data/RTL_Sources/spi_master.v:76$11": {
    "cell_type": "$logic_and",
    "signal_width": 1,
    "fan_in_count": 3,
    "has_multiply": 0,
    "has_divide": 0,
    "has_add": 0
  },
  "$logic_and$/home/svs_06/Google-Girl-Hackathon/Data/RTL_Sources/spi_master.v:76$13": {
    "cell_type": "$logic_and",
    "signal_width": 1,
    "fan_in_count": 3,
    "has_multiply": 0,
    "has_divide": 0,
    "has_add": 0
  },
  "$not$/home/svs_06/Google-Girl-Hackathon/Data/RTL_Sources/spi_master.v:34$4": {
    "cell_type": "$not",
    "signal_width": 1,
    "fan_in_count": 2,
    "has_multiply": 0,
    "has_divide": 0,
    "has_add": 0
  },
  "$procdff$100": {
    "cell_type": "$adff",
    "signal_width": 8,
    "fan_in_count": 4,
    "has_multiply": 0,
    "has_divide": 0,
    "has_add": 0
  },
  "$procdff$101": {
    "cell_type": "$adff",
    "signal_width": 4,
    "fan_in_count": 4,
    "has_multiply": 0,
    "has_divide": 0,
    "has_add": 0
  },
  "$procdff$102": {
    "cell_type": "$adff",
    "signal_width": 1,
    "fan_in_count": 4,
    "has_multiply": 0,
    "has_divide": 0,
    "has_add": 0
  },
  "$procdff$103": {
    "cell_type": "$adff",
    "signal_width": 2,
    "fan_in_count": 4,
    "has_multiply": 0,
    "has_divide": 0,
    "has_add": 0
  },
  "$procdff$104": {
    "cell_type": "$adff",
    "signal_width": 1,
    "fan_in_count": 4,
    "has_multiply": 0,
    "has_divide": 0,
    "has_add": 0
  },
  "$procdff$105": {
    "cell_type": "$adff",
    "signal_width": 8,
    "fan_in_count": 4,
    "has_multiply": 0,
    "has_divide": 0,
    "has_add": 0
  },
  "$procdff$96": {
    "cell_type": "$adff",
    "signal_width": 1,
    "fan_in_count": 4,
    "has_multiply": 0,
    "has_divide": 0,
    "has_add": 0
  },
  "$procdff$97": {
    "cell_type": "$adff",
    "signal_width": 1,
    "fan_in_count": 4,
    "has_multiply": 0,
    "has_divide": 0,
    "has_add": 0
  },
  "$procdff$98": {
    "cell_type": "$adff",
    "signal_width": 8,
    "fan_in_count": 4,
    "has_multiply": 0,
    "has_divide": 0,
    "has_add": 0
  },
  "$procdff$99": {
    "cell_type": "$adff",
    "signal_width": 8,
    "fan_in_count": 4,
    "has_multiply": 0,
    "has_divide": 0,
    "has_add": 0
  },
  "$procmux$24": {
    "cell_type": "$pmux",
    "signal_width": 2,
    "fan_in_count": 4,
    "has_multiply": 0,
    "has_divide": 0,
    "has_add": 0
  },
  "$procmux$31": {
    "cell_type": "$mux",
    "signal_width": 4,
    "fan_in_count": 4,
    "has_multiply": 0,
    "has_divide": 0,
    "has_add": 0
  },
  "$procmux$33": {
    "cell_type": "$mux",
    "signal_width": 4,
    "fan_in_count": 4,
    "has_multiply": 0,
    "has_divide": 0,
    "has_add": 0
  },
  "$procmux$35": {
    "cell_type": "$pmux",
    "signal_width": 8,
    "fan_in_count": 4,
    "has_multiply": 0,
    "has_divide": 0,
    "has_add": 0
  },
  "$procmux$39": {
    "cell_type": "$mux",
    "signal_width": 8,
    "fan_in_count": 4,
    "has_multiply": 0,
    "has_divide": 0,
    "has_add": 0
  },
  "$procmux$41": {
    "cell_type": "$mux",
    "signal_width": 8,
    "fan_in_count": 4,
    "has_multiply": 0,
    "has_divide": 0,
    "has_add": 0
  },
  "$procmux$43": {
    "cell_type": "$mux",
    "signal_width": 8,
    "fan_in_count": 4,
    "has_multiply": 0,
    "has_divide": 0,
    "has_add": 0
  },
  "$procmux$48": {
    "cell_type": "$mux",
    "signal_width": 8,
    "fan_in_count": 4,
    "has_multiply": 0,
    "has_divide": 0,
    "has_add": 0
  },
  "$procmux$50": {
    "cell_type": "$mux",
    "signal_width": 8,
    "fan_in_count": 4,
    "has_multiply": 0,
    "has_divide": 0,
    "has_add": 0
  },
  "$procmux$52": {
    "cell_type": "$mux",
    "signal_width": 8,
    "fan_in_count": 4,
    "has_multiply": 0,
    "has_divide": 0,
    "has_add": 0
  },
  "$procmux$54": {
    "cell_type": "$pmux",
    "signal_width": 3,
    "fan_in_count": 4,
    "has_multiply": 0,
    "has_divide": 0,
    "has_add": 0
  },
  "$procmux$58": {
    "cell_type": "$mux",
    "signal_width": 1,
    "fan_in_count": 4,
    "has_multiply": 0,
    "has_divide": 0,
    "has_add": 0
  },
  "$procmux$61": {
    "cell_type": "$pmux",
    "signal_width": 2,
    "fan_in_count": 4,
    "has_multiply": 0,
    "has_divide": 0,
    "has_add": 0
  },
  "$procmux$67": {
    "cell_type": "$mux",
    "signal_width": 2,
    "fan_in_count": 4,
    "has_multiply": 0,
    "has_divide": 0,
    "has_add": 0
  },
  "$procmux$75": {
    "cell_type": "$mux",
    "signal_width": 2,
    "fan_in_count": 4,
    "has_multiply": 0,
    "has_divide": 0,
    "has_add": 0
  },
  "$procmux$79": {
    "cell_type": "$pmux",
    "signal_width": 8,
    "fan_in_count": 4,
    "has_multiply": 0,
    "has_divide": 0,
    "has_add": 0
  },
  "$procmux$80_CMP0": {
    "cell_type": "$eq",
    "signal_width": 2,
    "fan_in_count": 3,
    "has_multiply": 0,
    "has_divide": 0,
    "has_add": 0
  },
  "$procmux$81_CMP0": {
    "cell_type": "$eq",
    "signal_width": 2,
    "fan_in_count": 3,
    "has_multiply": 0,
    "has_divide": 0,
    "has_add": 0
  },
  "$procmux$82_CMP0": {
    "cell_type": "$eq",
    "signal_width": 2,
    "fan_in_count": 3,
    "has_multiply": 0,
    "has_divide": 0,
    "has_add": 0
  },
  "$procmux$83_CMP0": {
    "cell_type": "$logic_not",
    "signal_width": 2,
    "fan_in_count": 2,
    "has_multiply": 0,
    "has_divide": 0,
    "has_add": 0
  },
  "$procmux$86": {
    "cell_type": "$mux",
    "signal_width": 8,
    "fan_in_count": 4,
    "has_multiply": 0,
    "has_divide": 0,
    "has_add": 0
  },
  "$procmux$88": {
    "cell_type": "$mux",
    "signal_width": 8,
    "fan_in_count": 4,
    "has_multiply": 0,
    "has_divide": 0,
    "has_add": 0
  },
  "$procmux$92": {
    "cell_type": "$mux",
    "signal_width": 1,
    "fan_in_count": 4,
    "has_multiply": 0,
    "has_divide": 0,
    "has_add": 0
  },
  "$procmux$94": {
    "cell_type": "$mux",
    "signal_width": 1,
    "fan_in_count": 4,
    "has_multiply": 0,
    "has_divide": 0,
    "has_add": 0
  },
  "$shiftx$/home/svs_06/Google-Girl-Hackathon/Data/RTL_Sources/spi_master.v:147$23": {
    "cell_type": "$shiftx",
    "signal_width": 32,
    "fan_in_count": 3,
    "has_multiply": 0,
    "has_divide": 0,
    "has_add": 0
  },
  "$sub$/home/svs_06/Google-Girl-Hackathon/Data/RTL_Sources/spi_master.v:147$22": {
    "cell_type": "$sub",
    "signal_width": 32,
    "fan_in_count": 3,
    "has_multiply": 0,
    "has_divide": 0,
    "has_add": 1
  },
  "$0\\bit_count[3:0]": {
    "net_size": 4,
    "signal_width": 4,
    "fan_in_count": 0,
    "has_multiply": 0,
    "has_divide": 0,
    "has_add": 0
  },
  "$0\\busy[0:0]": {
    "net_size": 1,
    "signal_width": 1,
    "fan_in_count": 0,
    "has_multiply": 0,
    "has_divide": 0,
    "has_add": 0
  },
  "$0\\clk_count[7:0]": {
    "net_size": 8,
    "signal_width": 8,
    "fan_in_count": 0,
    "has_multiply": 0,
    "has_divide": 0,
    "has_add": 0
  },
  "$0\\cs_n[0:0]": {
    "net_size": 1,
    "signal_width": 1,
    "fan_in_count": 0,
    "has_multiply": 0,
    "has_divide": 0,
    "has_add": 0
  },
  "$0\\data_out[7:0]": {
    "net_size": 8,
    "signal_width": 8,
    "fan_in_count": 0,
    "has_multiply": 0,
    "has_divide": 0,
    "has_add": 0
  },
  "$0\\rx_data[7:0]": {
    "net_size": 8,
    "signal_width": 8,
    "fan_in_count": 0,
    "has_multiply": 0,
    "has_divide": 0,
    "has_add": 0
  },
  "$0\\sclk[0:0]": {
    "net_size": 1,
    "signal_width": 1,
    "fan_in_count": 0,
    "has_multiply": 0,
    "has_divide": 0,
    "has_add": 0
  },
  "$0\\spi_clk_en[0:0]": {
    "net_size": 1,
    "signal_width": 1,
    "fan_in_count": 0,
    "has_multiply": 0,
    "has_divide": 0,
    "has_add": 0
  },
  "$0\\tx_data[7:0]": {
    "net_size": 8,
    "signal_width": 8,
    "fan_in_count": 0,
    "has_multiply": 0,
    "has_divide": 0,
    "has_add": 0
  },
  "$2\\next_state[1:0]": {
    "net_size": 2,
    "signal_width": 2,
    "fan_in_count": 0,
    "has_multiply": 0,
    "has_divide": 0,
    "has_add": 0
  },
  "$3\\next_state[1:0]": {
    "net_size": 2,
    "signal_width": 2,
    "fan_in_count": 0,
    "has_multiply": 0,
    "has_divide": 0,
    "has_add": 0
  },
  "$add$/home/svs_06/Google-Girl-Hackathon/Data/RTL_Sources/spi_master.v:131$21_Y": {
    "net_size": 32,
    "signal_width": 32,
    "fan_in_count": 0,
    "has_multiply": 0,
    "has_divide": 0,
    "has_add": 0
  },
  "$add$/home/svs_06/Google-Girl-Hackathon/Data/RTL_Sources/spi_master.v:38$5_Y": {
    "net_size": 32,
    "signal_width": 32,
    "fan_in_count": 0,
    "has_multiply": 0,
    "has_divide": 0,
    "has_add": 0
  },
  "$auto$opt_reduce.cc:132:opt_mux$107": {
    "net_size": 1,
    "signal_width": 1,
    "fan_in_count": 0,
    "has_multiply": 0,
    "has_divide": 0,
    "has_add": 0
  },
  "$auto$opt_reduce.cc:132:opt_mux$109": {
    "net_size": 1,
    "signal_width": 1,
    "fan_in_count": 0,
    "has_multiply": 0,
    "has_divide": 0,
    "has_add": 0
  },
  "$eq$/home/svs_06/Google-Girl-Hackathon/Data/RTL_Sources/spi_master.v:126$19_Y": {
    "net_size": 1,
    "signal_width": 1,
    "fan_in_count": 0,
    "has_multiply": 0,
    "has_divide": 0,
    "has_add": 0
  },
  "$eq$/home/svs_06/Google-Girl-Hackathon/Data/RTL_Sources/spi_master.v:76$9_Y": {
    "net_size": 1,
    "signal_width": 1,
    "fan_in_count": 0,
    "has_multiply": 0,
    "has_divide": 0,
    "has_add": 0
  },
  "$logic_and$/home/svs_06/Google-Girl-Hackathon/Data/RTL_Sources/spi_master.v:76$11_Y": {
    "net_size": 1,
    "signal_width": 1,
    "fan_in_count": 0,
    "has_multiply": 0,
    "has_divide": 0,
    "has_add": 0
  },
  "$logic_and$/home/svs_06/Google-Girl-Hackathon/Data/RTL_Sources/spi_master.v:76$13_Y": {
    "net_size": 1,
    "signal_width": 1,
    "fan_in_count": 0,
    "has_multiply": 0,
    "has_divide": 0,
    "has_add": 0
  },
  "$not$/home/svs_06/Google-Girl-Hackathon/Data/RTL_Sources/spi_master.v:34$4_Y": {
    "net_size": 1,
    "signal_width": 1,
    "fan_in_count": 0,
    "has_multiply": 0,
    "has_divide": 0,
    "has_add": 0
  },
  "$procmux$25_CMP": {
    "net_size": 1,
    "signal_width": 1,
    "fan_in_count": 0,
    "has_multiply": 0,
    "has_divide": 0,
    "has_add": 0
  },
  "$procmux$26_CMP": {
    "net_size": 1,
    "signal_width": 1,
    "fan_in_count": 0,
    "has_multiply": 0,
    "has_divide": 0,
    "has_add": 0
  },
  "$procmux$27_CMP": {
    "net_size": 1,
    "signal_width": 1,
    "fan_in_count": 0,
    "has_multiply": 0,
    "has_divide": 0,
    "has_add": 0
  },
  "$procmux$31_Y": {
    "net_size": 4,
    "signal_width": 4,
    "fan_in_count": 0,
    "has_multiply": 0,
    "has_divide": 0,
    "has_add": 0
  },
  "$procmux$33_Y": {
    "net_size": 4,
    "signal_width": 4,
    "fan_in_count": 0,
    "has_multiply": 0,
    "has_divide": 0,
    "has_add": 0
  },
  "$procmux$36_CMP": {
    "net_size": 1,
    "signal_width": 1,
    "fan_in_count": 0,
    "has_multiply": 0,
    "has_divide": 0,
    "has_add": 0
  },
  "$procmux$39_Y": {
    "net_size": 8,
    "signal_width": 8,
    "fan_in_count": 0,
    "has_multiply": 0,
    "has_divide": 0,
    "has_add": 0
  },
  "$procmux$41_Y": {
    "net_size": 8,
    "signal_width": 8,
    "fan_in_count": 0,
    "has_multiply": 0,
    "has_divide": 0,
    "has_add": 0
  },
  "$procmux$48_Y": {
    "net_size": 8,
    "signal_width": 8,
    "fan_in_count": 0,
    "has_multiply": 0,
    "has_divide": 0,
    "has_add": 0
  },
  "$procmux$58_Y": {
    "net_size": 1,
    "signal_width": 1,
    "fan_in_count": 0,
    "has_multiply": 0,
    "has_divide": 0,
    "has_add": 0
  },
  "$procmux$86_Y": {
    "net_size": 8,
    "signal_width": 8,
    "fan_in_count": 0,
    "has_multiply": 0,
    "has_divide": 0,
    "has_add": 0
  },
  "$procmux$92_Y": {
    "net_size": 1,
    "signal_width": 1,
    "fan_in_count": 0,
    "has_multiply": 0,
    "has_divide": 0,
    "has_add": 0
  },
  "$sub$/home/svs_06/Google-Girl-Hackathon/Data/RTL_Sources/spi_master.v:147$22_Y": {
    "net_size": 32,
    "signal_width": 32,
    "fan_in_count": 0,
    "has_multiply": 0,
    "has_divide": 0,
    "has_add": 0
  },
  "bit_count": {
    "net_size": 4,
    "signal_width": 4,
    "fan_in_count": 0,
    "has_multiply": 0,
    "has_divide": 0,
    "has_add": 0
  },
  "busy": {
    "net_size": 1,
    "signal_width": 1,
    "fan_in_count": 0,
    "has_multiply": 0,
    "has_divide": 0,
    "has_add": 0
  },
  "clk": {
    "net_size": 1,
    "signal_width": 1,
    "fan_in_count": 0,
    "has_multiply": 0,
    "has_divide": 0,
    "has_add": 0
  },
  "clk_count": {
    "net_size": 8,
    "signal_width": 8,
    "fan_in_count": 0,
    "has_multiply": 0,
    "has_divide": 0,
    "has_add": 0
  },
  "cs_n": {
    "net_size": 1,
    "signal_width": 1,
    "fan_in_count": 0,
    "has_multiply": 0,
    "has_divide": 0,
    "has_add": 0
  },
  "data_in": {
    "net_size": 8,
    "signal_width": 8,
    "fan_in_count": 0,
    "has_multiply": 0,
    "has_divide": 0,
    "has_add": 0
  },
  "data_out": {
    "net_size": 8,
    "signal_width": 8,
    "fan_in_count": 0,
    "has_multiply": 0,
    "has_divide": 0,
    "has_add": 0
  },
  "miso": {
    "net_size": 1,
    "signal_width": 1,
    "fan_in_count": 0,
    "has_multiply": 0,
    "has_divide": 0,
    "has_add": 0
  },
  "mosi": {
    "net_size": 1,
    "signal_width": 1,
    "fan_in_count": 0,
    "has_multiply": 0,
    "has_divide": 0,
    "has_add": 0
  },
  "next_state": {
    "net_size": 2,
    "signal_width": 2,
    "fan_in_count": 0,
    "has_multiply": 0,
    "has_divide": 0,
    "has_add": 0
  },
  "rst_n": {
    "net_size": 1,
    "signal_width": 1,
    "fan_in_count": 0,
    "has_multiply": 0,
    "has_divide": 0,
    "has_add": 0
  },
  "rx_data": {
    "net_size": 8,
    "signal_width": 8,
    "fan_in_count": 0,
    "has_multiply": 0,
    "has_divide": 0,
    "has_add": 0
  },
  "sample_edge": {
    "net_size": 1,
    "signal_width": 1,
    "fan_in_count": 0,
    "has_multiply": 0,
    "has_divide": 0,
    "has_add": 0
  },
  "sclk": {
    "net_size": 1,
    "signal_width": 1,
    "fan_in_count": 0,
    "has_multiply": 0,
    "has_divide": 0,
    "has_add": 0
  },
  "spi_clk_en": {
    "net_size": 1,
    "signal_width": 1,
    "fan_in_count": 0,
    "has_multiply": 0,
    "has_divide": 0,
    "has_add": 0
  },
  "start": {
    "net_size": 1,
    "signal_width": 1,
    "fan_in_count": 0,
    "has_multiply": 0,
    "has_divide": 0,
    "has_add": 0
  },
  "state": {
    "net_size": 2,
    "signal_width": 2,
    "fan_in_count": 0,
    "has_multiply": 0,
    "has_divide": 0,
    "has_add": 0
  },
  "tx_data": {
    "net_size": 8,
    "signal_width": 8,
    "fan_in_count": 0,
    "has_multiply": 0,
    "has_divide": 0,
    "has_add": 0
  }
}